nessiedemo/__init__.py
nessiedemo/delta_spark.py
nessiedemo/demo.py
nessiedemo/flink.py
nessiedemo/iceberg_spark.py
nessiedemo/spark_base.py
nessiedemo-0.0.19.dist-info/METADATA
nessiedemo-0.0.19.dist-info/WHEEL
nessiedemo-0.0.19.dist-info/top_level.txt
nessiedemo-0.0.19.dist-info/RECORD
