Metadata-Version: 2.1
Name: nessiedemo
Version: 0.0.19
Summary: Project Nessie Demos Helper
Home-page: https://github.com/projectnessie/nessie
Author: Robert Stupp
Author-email: nessie-release-builder@dremio.com
License: Apache Software License 2.0
Keywords: nessiedemo
Platform: UNKNOWN
Classifier: Development Status :: 2 - Pre-Alpha
Classifier: Intended Audience :: Developers
Classifier: License :: OSI Approved :: Apache Software License
Classifier: Natural Language :: English
Classifier: Programming Language :: Python :: 3
Classifier: Programming Language :: Python :: 3.7
Classifier: Programming Language :: Python :: 3.8
Classifier: Programming Language :: Python :: 3.9
Requires-Python: >=3.7
Requires-Dist: PyYAML (>=5.4.0)
Requires-Dist: requests (>=2.23.0)
Requires-Dist: pandas-profiling (>=3.0.0)
